.coveragerc
.gitignore
.pre-commit-config.yaml
.travis.yml
AUTHORS.rst
LICENSE.txt
README.rst
dodo.py
pytest.ini
requirements-dev.txt
requirements-doc.txt
requirements-test.txt
requirements.txt
setup.cfg
setup.py
tox.ini
bin/cdocs.sh
bin/ctest.sh
docs/Makefile
docs/about-include.rst
docs/about.rst
docs/authors.rst
docs/changelog.rst
docs/conf.py
docs/developer.rst
docs/index.rst
docs/license.rst
docs/pysimoa.bib
docs/reference.rst
docs/setup.rst
docs/tutorial.rst
docs/user.rst
docs/zbib.rst
docs/_static/.gitignore
docs/_static/cc-by.pdf
docs/_static/cc-by.svg
simoa/__init__.py
simoa/mser.py
simoa/nskart.py
simoa/stats.py
simoa.egg-info/PKG-INFO
simoa.egg-info/SOURCES.txt
simoa.egg-info/dependency_links.txt
simoa.egg-info/entry_points.txt
simoa.egg-info/namespace_packages.txt
simoa.egg-info/not-zip-safe
simoa.egg-info/requires.txt
simoa.egg-info/top_level.txt
simoa/test/__init__.py
simoa/test/test_mser.py
simoa/test/test_nskart.py
simoa/test/test_stats.py