Metadata-Version: 1.1
Name: simoa
Version: 0.4.1
Summary: Scientific Python package for Simulation Output Analysis
Home-page: UNKNOWN
Author: Andreas Sorge
Author-email: pysimoa@asorge.de
License: apache
Platform: UNKNOWN
Classifier: Development Status :: 3 - Alpha
Classifier: License :: OSI Approved :: Apache Software License
Classifier: Programming Language :: Python
Classifier: Programming Language :: Python :: 2.7
Classifier: Programming Language :: Python :: 3.4
Classifier: Topic :: Scientific/Engineering
Classifier: Intended Audience :: Science/Research
